odoo/addons/stock_picking_return_show_lot/README.rst
odoo/addons/stock_picking_return_show_lot/__init__.py
odoo/addons/stock_picking_return_show_lot/__manifest__.py
odoo/addons/stock_picking_return_show_lot/i18n/stock_picking_return_show_lot.pot
odoo/addons/stock_picking_return_show_lot/readme/CONTRIBUTORS.rst
odoo/addons/stock_picking_return_show_lot/readme/DESCRIPTION.rst
odoo/addons/stock_picking_return_show_lot/static/description/icon.png
odoo/addons/stock_picking_return_show_lot/static/description/index.html
odoo/addons/stock_picking_return_show_lot/wizards/__init__.py
odoo/addons/stock_picking_return_show_lot/wizards/stock_return_picking.py
odoo/addons/stock_picking_return_show_lot/wizards/stock_return_picking.xml
odoo14_addon_stock_picking_return_show_lot-14.0.1.0.1.dist-info/METADATA
odoo14_addon_stock_picking_return_show_lot-14.0.1.0.1.dist-info/WHEEL
odoo14_addon_stock_picking_return_show_lot-14.0.1.0.1.dist-info/top_level.txt
odoo14_addon_stock_picking_return_show_lot-14.0.1.0.1.dist-info/RECORD
